{"kind":"identitytoolkit#DownloadAccountResponse","users":[{"localId":"1AYRQQTkzZsMY28oXzbb2SMjo2FX","createdAt":"1771524657150","lastLoginAt":"1771954692325","passwordHash":"fakeHash:salt=fakeSaltc6M5Oq6xz3J4vjyZZVwI:password=123456","salt":"fakeSaltc6M5Oq6xz3J4vjyZZVwI","passwordUpdatedAt":1771954611308,"providerUserInfo":[{"providerId":"password","email":"jair@gmail.com","federatedId":"jair@gmail.com","rawId":"jair@gmail.com"}],"validSince":"1771954611","email":"jair@gmail.com","emailVerified":false,"disabled":false,"lastRefreshAt":"2026-02-24T19:28:14.418Z"},{"localId":"8jlqAz90nDxYiwDUOhoeFibslaeo","createdAt":"1771690027403","lastLoginAt":"1771955754790","passwordHash":"fakeHash:salt=fakeSaltZB9oH3ettCR6LJ71cjMu:password=123456","salt":"fakeSaltZB9oH3ettCR6LJ71cjMu","passwordUpdatedAt":1771954611309,"providerUserInfo":[{"providerId":"password","email":"hudson@gmail.com","federatedId":"hudson@gmail.com","rawId":"hudson@gmail.com"}],"validSince":"1771954611","email":"hudson@gmail.com","emailVerified":false,"disabled":false,"lastRefreshAt":"2026-02-24T18:50:54.817Z"},{"localId":"Bz6OvZ0e58jSX6aPpyc6WPVj4QQe","createdAt":"1771517673646","lastLoginAt":"1771958898542","displayName":"Jandesson Moraes","photoUrl":"","passwordHash":"fakeHash:salt=fakeSaltpHOT58dCagr64g1prIQn:password=Jg421926","salt":"fakeSaltpHOT58dCagr64g1prIQn","passwordUpdatedAt":1771954611309,"providerUserInfo":[{"providerId":"password","email":"jandessonmoraes@gmail.com","federatedId":"jandessonmoraes@gmail.com","rawId":"jandessonmoraes@gmail.com","displayName":"Jandesson Moraes","photoUrl":""},{"providerId":"phone","phoneNumber":"+5592991903278","rawId":"+5592991903278"}],"phoneNumber":"+5592991903278","validSince":"1771954611","email":"jandessonmoraes@gmail.com","emailVerified":false,"disabled":false,"lastRefreshAt":"2026-02-24T18:48:18.542Z"},{"localId":"HHXxE1uKfM1QchKD2tmCWU4R9P7H","createdAt":"1771526256484","lastLoginAt":"1771526256484","validSince":"1771954611","emailVerified":false,"disabled":false},{"localId":"IaWYw9ImAHhbaQqmYnlyIgaHIiCQ","createdAt":"1771615872924","lastLoginAt":"1771615872924","validSince":"1771954611","emailVerified":false,"disabled":false},{"localId":"TswOeySZL3aeaQeZygBXJqESgITL","createdAt":"1771689208522","lastLoginAt":"1771958896334","passwordHash":"fakeHash:salt=fakeSaltgXAkRhzxNqqMaQSfyKbx:password=123456","salt":"fakeSaltgXAkRhzxNqqMaQSfyKbx","passwordUpdatedAt":1771954611309,"providerUserInfo":[{"providerId":"password","email":"jhans@gmail.com","federatedId":"jhans@gmail.com","rawId":"jhans@gmail.com"}],"validSince":"1771954611","email":"jhans@gmail.com","emailVerified":false,"disabled":false,"lastRefreshAt":"2026-02-24T18:55:53.422Z"},{"localId":"WALox61vVeSwiyhD65hizmJpnSSS","createdAt":"1771680202397","lastLoginAt":"1771680202397","validSince":"1771954611","emailVerified":false,"disabled":false},{"localId":"hkfIlvjn1ph79GuTeeN9TMCsbztz","createdAt":"1771544024038","lastLoginAt":"1771544024038","validSince":"1771954611","emailVerified":false,"disabled":false},{"localId":"jBZUkB1xGG7q3tjRrPcDp63fbFYX","createdAt":"1771536370520","lastLoginAt":"1771689163745","passwordHash":"fakeHash:salt=fakeSaltihRer01Ygz8xgbkjGRDg:password=123456","salt":"fakeSaltihRer01Ygz8xgbkjGRDg","passwordUpdatedAt":1771954611309,"providerUserInfo":[{"providerId":"password","email":"gih@gmail.com","federatedId":"gih@gmail.com","rawId":"gih@gmail.com"}],"validSince":"1771954611","email":"gih@gmail.com","emailVerified":false,"disabled":false},{"localId":"n0EuN7qTQsd9gdbPh8RZCXNZvCzg","createdAt":"1771518021884","lastLoginAt":"1771536332002","passwordHash":"fakeHash:salt=fakeSaltzmfmas7U2YO2XYsIybR4:password=123456","salt":"fakeSaltzmfmas7U2YO2XYsIybR4","passwordUpdatedAt":1771954611309,"providerUserInfo":[{"providerId":"password","email":"jhan@gmail.com","federatedId":"jhan@gmail.com","rawId":"jhan@gmail.com"}],"validSince":"1771954611","email":"jhan@gmail.com","emailVerified":false,"disabled":false},{"localId":"pJ62GlWtZUyr1Zw87scchAQ9kg28","createdAt":"1771526403273","lastLoginAt":"1771526403273","validSince":"1771954611","emailVerified":false,"disabled":false},{"localId":"pd0aDuqHxElHn3UVs4I1ThaGpgqn","createdAt":"1771940815847","lastLoginAt":"1771940815847","passwordHash":"fakeHash:salt=fakeSalt6ocy98nfPfaMmAlKLIpb:password=123456","salt":"fakeSalt6ocy98nfPfaMmAlKLIpb","passwordUpdatedAt":1771954611309,"providerUserInfo":[{"providerId":"password","email":"jhanss@gmail.com","federatedId":"jhanss@gmail.com","rawId":"jhanss@gmail.com"}],"validSince":"1771954611","email":"jhanss@gmail.com","emailVerified":false,"disabled":false},{"localId":"ygvlaAd7SsqJuBzGovDhLuiD5m2u","createdAt":"1771528430196","lastLoginAt":"1771528430196","validSince":"1771954611","emailVerified":false,"disabled":false}]}